authenticator/__init__.py
authenticator/admin.py
authenticator/apps.py
authenticator/models.py
authenticator/tests.py
authenticator/urls.py
authenticator/views.py
authenticator/migrations/__init__.py
authenticator/templatetags/__init__.py
authenticator/templatetags/tower_tags.py
tests/__init__.py
tests/urls.py
shopcloud_django_authenticator-1.15.0.dist-info/LICENSE
shopcloud_django_authenticator-1.15.0.dist-info/METADATA
shopcloud_django_authenticator-1.15.0.dist-info/WHEEL
shopcloud_django_authenticator-1.15.0.dist-info/top_level.txt
shopcloud_django_authenticator-1.15.0.dist-info/RECORD
