Metadata-Version: 2.1
Name: shopcloud-django-authenticator
Version: 1.15.0
Summary: A Module for single sign in
Home-page: https://github.com/Talk-Point/shopcloud-django-authenticator
Author: Konstantin Stoldt
Author-email: konstantin.stoldt@talk-point.de
License: MIT
License-File: LICENSE
Requires-Dist: Django>=3.2
Requires-Dist: djangorestframework
Requires-Dist: django-filter
Requires-Dist: markdown
Requires-Dist: pyjwt
